math_lab/__init__.py
math_lab/calc.py
esercitazione_cicd-0.1.dist-info/METADATA
esercitazione_cicd-0.1.dist-info/WHEEL
esercitazione_cicd-0.1.dist-info/top_level.txt
esercitazione_cicd-0.1.dist-info/RECORD
